{"baseBpm":120,"musics":[{"bpm":120,"baseBeats":0.25,"scores":["(c2.d2)[L],(d2.b1)[K],c4[J],c3[KL],3<c1[N],e1[N],g1[N],(c.e.g)[N],c1[N],e1[N],g1[N],(c.e.g)[N],c1[N],e1[N],g1[N],(c.e.g)[N],c1[N],e1[N],g1[N],(c.e.g)[N],c1[N],e1[N],g1[N],(c.e.g)[N],c1[N],e1[N],g1[N],(c.e.g)[N],c1[N],e1[N],g1[N],(c.e.g)[N],c1[N],e1[N],g1[N],(c.e.g)[N],(c.e.g)[N],(c.e.g)[N],(c.e.g)[N],(c.e.g)[N],(c.e.g)[N],(c.e.g)[N],(c.e.g)[N],(c.e.g)[N],(c.e.g)[N],(c.e.g)[N],(c.e.g)[N],(c.e.g)[N],(c.e.g)[N],(c.e.g)[N],(c.e.g)[N],(c.e.g)[N],(c.e.g)[N],(c.e.g)[N],(c.e.g)[N],(c.e.g)[N],(c.e.g)[N],(c.e.g)[N],(c.e.g)[N],(c.e.g)[N],(c.e.g)[N],(c.e.g)[N],(c.e.g)[N],(c.e.g)[N]>,(b4.c5)[I],(c1~d1~e1~f1~g1~a1~b1~a1~g1~f1~e1~d1)[KL],(c1~d1~e1~f1~g1~a1~b1~a1~g1~f1~e1~d1)[KL],(c1~d1~e1~f1~g1~a1~b1~a1~g1~f1~e1~d1)[KL],(c1~d1~e1~f1~g1~a1~b1~a1~g1~f1~e1~d1)[KL],(c1~d1~e1~f1~g1~a1~b1~a1~g1~f1~e1~d1)[KL],(c1~d1~e1~f1~g1~a1~b1~a1~g1~f1~e1~d1)[KL],(A-3.#A-3)[L],S,6<(e1.c2)[J]>,6<(g1.b1)[K]>,f1[K];6<(e1.c2)[K]>,(a1.e2)[K],6<(e2.g2)[K]>,(d2.a2)[K];6<(a1.f2)[K]>,c2[K],6<(g1.e2)[K]>,e1[K];6<(d1.f1)[K]>,(a1.c2)[K],6<(g1.c2)[K]>,c2[L],b1[L];c2[L],b1[L],c2[L],e1[L],g1[K],b1[K];c2[K],e2[K],g2[L],e2[L],g2[L],a2[L];f2[L],e2[L],d2[L],f2[L],e2[L],d2[L],c2[L],b1[L];a1[L],f1[L],c2[K],b1[L],d1[L],c2[L],d2[M],c2[M];(#d2)[KL],(#g2)[KL],(#a2)[KL],(#G-1.b2)[M],U,(#a2)[M],(#g.b2)[M],U,(#a2)[M],(#G-1.b2)[M],U,(#a2)[M],(#g.#g2)[M],U,(#d2)[M],(#c.e2)[K],(#g.b.b2)[M],U,(b2)[M],(#c)[M],U,(e1)[M],(#g1)[K],(#F-1.#c2.#a2)[M],U,(#c2.#g2)[M],(#f.#a2)[M],U,(#g2)[M],(#F-1.#a2)[M],U,(#g2)[M],(#f.#f2)[M],U,(#c2)[M],(B-1.#d2)[K],(#f.#a.#a2)[M],U,(#a2)[M],(B-1)[M],U,(#d1)[M],(#f1)[K],(E-1.#g2)[M],U,(#f2)[M],(e.#g2)[M],U,(#f2)[M],(E-1.#g2)[M],U,(#f2)[M],(e.#g2)[M],U,(#d3)[M],(#c.#c3)[M],U,(b2)[M],(b.#c3)[K],(e1)[M],U,(#g1)[M],(#g.#c2)[K],(#A-1.#c3)[M],U,(b2)[M],(e.#a2)[M],U,(b2)[M],(#A-1.#c3)[M],U,(#d3)[M],(e.#g.#c3)[M],U,(#g2)[M],(#D-1.#a2)[M],U,(#a)[M],(#d.g.#d1)[M],U,(f1)[M],(#D-1.g1)[M],U,(#g1)[M],(#a1)[K],(#G-1.b1)[M],U,(#a1)[M],(#g.b1)[M],U,(#a1)[M],(#G-1.b1)[M],U,(#a1)[M],(#g.#g1)[M],U,(#d1)[M],(#c.e1)[K],(#g.b1)[M],U,(b1)[M],(#c)[M],U,(#c1)[M],(#g.#d1)[K],(#F-1.#a1)[M],U,(#g1)[M],(#f.#a1)[M],U,(#g1)[M],(#F-1.#a1)[M],U,(#g1)[M],(#f.#f1)[M],U,(#c1)[M],(B-1.#d1)[K],(#f.#a1)[M],U,(#a1)[M],(B-1)[M],U,(#c1)[M],(#f.#a.#d1)[K],3<(c.e.g)[N],(c.e.g)[N],(c.e.g)[N],(c.e.g)[N],(c.e.g)[N],(c.e.g)[N],(c.e.g)[N],(c.e.g)[N],(c.e.g)[N],(c.e.g)[N],(c.e.g)[N],(c.e.g)[N],(c.e.g)[N],(c.e.g)[N],(c.e.g)[N],(c.e.g)[N],(c.e.g)[N],(c.e.g)[N],(c.e.g)[N],(c.e.g)[N],(c.e.g)[N],(c.e.g)[N],(c.e.g)[N],(c.e.g)[N],(c.e.g)[N],(c.e.g)[N],(c.e.g)[N],(c.e.g)[N],(c.e.g)[N],(c.e.g)[N],(c.e.g)[N],(c.e.g)[N],(c.e.g)[N],(c.e.g)[N],(c.e.g)[N],(c.e.g)[N],(c.e.g)[N],(c.e.g)[N],(c.e.g)[N],(c.e.g)[N],(c.e.g)[N],(c.e.g)[N],(c.e.g)[N],(c.e.g)[N],(c.e.g)[N],(c.e.g)[N],(c.e.g)[N],(c.e.g)[N],(c.e.g)[N],(c.e.g)[N],(c.e.g)[N],(c.e.g)[N],(c.e.g)[N],(c.e.g)[N],(c.e.g)[N],(c.e.g)[N],(c.e.g)[N],(c.e.g)[N],(c.e.g)[N],(c.e.g)[N],(c.e.g)[N],(c.e.g)[N],(c.e.g)[N],(c.e.g)[N],(c.e.g)[N],(c.e.g)[N],(c.e.g)[N],(c.e.g)[N],(c.e.g)[N],(c.e.g)[N],(c.e.g)[N],(c.e.g)[N],(c.e.g)[N],(c.e.g)[N],(c.e.g)[N],(c.e.g)[N],(c.e.g)[N],(c.e.g)[N],(c.e.g)[N],(c.e.g)[N],(c.e.g)[N],(c.e.g)[N],(c.e.g)[N],(c.e.g)[N],(c.e.g)[N],(c.e.g)[N],(c.e.g)[N],(c.e.g)[N],(c.e.g)[N],(c.e.g)[N],(c.e.g)[N],(c.e.g)[N],(c.e.g)[N],(c.e.g)[N],(c.e.g)[N],(c.e.g)[N],(c.e.g)[N],(c.e.g)[N],(c.e.g)[N],(c.e.g)[N],(c.e.g)[N],(c.e.g)[N],(c.e.g)[N],(c.e.g)[N],(c.e.g)[N],(c.e.g)[N],(c.e.g)[N],(c.e.g)[N],(c.e.g)[N],(c.e.g)[N],(c.e.g)[N],(c.e.g)[N],(c.e.g)[N],(c.e.g)[N],(c.e.g)[N],(c.e.g)[N],(c.e.g)[N],(c.e.g)[N],(c.e.g)[N],(c.e.g)[N],(c.e.g)[N],(c.e.g)[N],(c.e.g)[N],(c.e.g)[N],(c.e.g)[N],(c.e.g)[N],(c.e.g)[N],(c.e.g)[N],(c.e.g)[N]>,3<c5[N],c5[N],c5[N],c5[N],c5[N],c5[N],c5[N],c5[N],c5[N],c5[N],c5[N],c5[N],c5[N],c5[N],c5[N],c5[N],c5[N],c5[N],c5[N],c5[N],c5[N],c5[N],c5[N],c5[N],c5[N],c5[N],c5[N],c5[N],c5[N],c5[N],c5[N],c5[N],c5[N],c5[N],c5[N],c5[N],c5[N],c5[N],c5[N],c5[N],c5[N],c5[N],c5[N],c5[N],c5[N],c5[N],c5[N],c5[N],c5[N],c5[N],c5[N],c5[N],c5[N],c5[N],c5[N],c5[N],c5[N],c5[N],c5[N],c5[N],c5[N],c5[N],c5[N],c5[N],c5[N],c5[N],c5[N],c5[N],c5[N],c5[N],c5[N],c5[N],c5[N],c5[N],c5[N],c5[N],c5[N],c5[N],c5[N],c5[N],c5[N],c5[N],c5[N],c5[N],c5[N],c5[N],c5[N],c5[N],c5[N],c5[N],c5[N],c5[N],c5[N],c5[N],c5[N],c5[N],c5[N],c5[N],c5[N],c5[N],c5[N],c5[N],c5[N],c5[N],c5[N],c5[N],c5[N],c5[N],c5[N],c5[N],c5[N],c5[N],c5[N],c5[N],c5[N],c5[N],c5[N],c5[N],c5[N],c5[N],c5[N],c5[N],c5[N],c5[N],c5[N],c5[N],c5[N],c5[N],c5[N],c5[N],c5[N],c5[N],c5[N],c5[N],c5[N],c5[N],c5[N],c5[N],c5[N],c5[N],c5[N],c5[N],c5[N],c5[N],c5[N],c5[N],c5[N],c5[N],c5[N],c5[N],c5[N],c5[N],c5[N],c5[N],c5[N],c5[N],c5[N],c5[N],c5[N],c5[N],c5[N],c5[N],c5[N],c5[N],c5[N],c5[N],c5[N],c5[N],c5[N],c5[N],c5[N],c5[N],c5[N],c5[N],c5[N],c5[N],c5[N],c5[N],c5[N],c5[N],c5[N],c5[N],c5[N],c5[N],c5[N],c5[N],c5[N],c5[N],c5[N],c5[N],c5[N],c5[N],c5[N],c5[N],c5[N],c5[N],c5[N],c5[N],c5[N],c5[N],c5[N],c5[N],c5[N],c5[N],c5[N],c5[N],c5[N],c5[N]>,T,8<(#a2~c3~d3~#d3~f3~g3~a3)[K],(c5~b4~a4~g4~f4~e4~d4~c4~b3~a3~g3~f3~e3~d3~c3~b2~a2~g2~f2~e2~d2~c2~b1~a1~g1~f1~e1~d1~c1~b~a~g~f~e~d~c)[LM]>,8<(b1~d1~b~g~g~G-1)[LM],(A-1~e~a~e1~d1~a~e1~a1~b1)[J],(c5~b4~a4~g4~f4~e4~d4~c4~b3~a3~g3~f3~e3~d3~c3~b2~a2~g2~f2~e2~d2~c2~b1~a1~g1~f1~e1~d1~c1~b~a~g~f~e~d~c)[KLM]>,8<(a~b~#c1~d1~e1~#f1~g1)[L];(a1~b1~#c2~d2~e2~#f2~g2~a2~b2~#c3)[K],(c5~b4~#a4~a4~#g4~g4~#f4~f4~e4~#d4~d4~#c4~c4~b3~#a3~a3~#g3~g3~#f3~f3~e3~#d3~d3~#c3~c3~b2~#a2~a2~#g2~g2~#f2~f2~e2~#d2~d2~#c2~c2~b1~#a1~a1~#g1~g1~#f1~f1~e1~#d1~d1~#c1~c1~b~#a~a~#g~g~#f~f~e~#d~d~#c~c~B-1~#A-1~A-1~#G-1~G-1~#F-1~F-1~E-1~#D-1~D-1~#C-1~C-1~B-2~#A-2~A-2~#G-2~G-2~#F-2~F-2~E-2~#D-2~D-2~#C-2~C-2~B-3~#A-3~A-3)[KLM]>,3<e[N],#a[N],#c1[N],g1[N],e1[N],#a1[N],#c2[N],g2[N],#d[N],a[N],c1[N],#f1[N],a1[N],#d2[N],#f2[N],c3[N],d[N],#g[N],b[N],f1[N],d2[N],#g2[N],b2[N],f3[N],#c[N],g[N],#a[N],e1[N],g2[N],#c3[N],e3[N],#a3[N],#A-1[N],e[N],g[N],#c1[N],#a1[N],e2[N],g2[N],#c3[N],A-1[N],#d[N],#f[N],c1[N],#d2[N],a2[N],c3[N],#f3[N],#G-1[N],d[N],f[N],b[N],#g2[N],d3[N],f3[N],b3[N],G-1[N],#c[N],e[N],#a[N],#c3[N],g3[N],#a3[N],e4[N],E-1[N],#A-1[N],#c[N],g[N],#d2[N],#a2[N],#c3[N],g3[N],#D-1[N],A-1[N],c[N],#f[N],a2[N],#d3[N],#f3[N],c4[N],D-1[N],#G-1[N],B-1[N],f[N],d3[N],#g3[N],b3[N],f4[N],#C-1[N],G-1[N],#A-1[N],e[N],e3[N],#a3[N],#c4[N],g4[N],d[N],#g[N],b[N],f1[N],d2[N],#g2[N],b2[N],#f3[N],#C-1[N],G-1[N],#A-1[N],e[N],e3[N],#a3[N],#c4[N],g4[N],d[N],#g[N],b[N],f1[N],d2[N],#g2[N],b2[N],#f3[N],(#A-2.#C-1.G-1)[N],A-1[N],#A-1[N],#c[N],d[N],e[N],f[N],(#A-2.#C-1.F-1.g)[N],a[N],#a[N],#c1[N],d1[N],e1[N],f1[N],(#A-2.#C-1.G-1.g1)[N],a1[N],#a1[N],#c2[N],d2[N],e2[N],f2[N],(#A-2.#C-1.E-1.g2)[N],a2[N],#a2[N],#c3[N],d3[N],e3[N],f3[N],(#A-2.#C-1.F-1.g3)[N],a3[N],#a3[N],#c4[N],d4[N],e4[N],f4[N],(#A-2.D-1.g4)[N],f4[N],e4[N],d4[N],#c4[N],#a3[N],a3[N],(#A-2.#C-1.E-1.g3)[N],f3[N],e3[N],d3[N],#c3[N],#a2[N],a2[N],g2[N],f2[N],e2[N],d2[N],#c2[N],#a1[N],a1[N],(#A-2.#C-1.G-1.g1)[N],f1[N],e1[N],d1[N],#c1[N],#a[N],a[N],(#A-2.#C-1.G-1.g)[N],f[N],e[N],(#A-2.#C-1.A-1.d)[N],#c[N],#A-1[N],(#A-2.#C-1.G-1)[N],A-1[N],#A-1[N],(#A-2.#C-1.F-1.#c)[N],d[N],e[N],f[N],(#A-2.#C-1.E-1.g)[N],a[N],#a[N],#c1[N],(#A-2.D-1.d1)[N],e1[N],f1[N],(#A-2.#C-1.F-1.g1)[N],a1[N],#a1[N],#c2[N],d2[N],e2[N],f2[N],(#A-2.#C-1.G-1.g2)[N],a2[N],#a2[N],#c3[N],d3[N],e3[N],f3[N],(#A-2.#C-1.F-1.g3)[N],a3[N],#a3[N],#c4[N],d4[N],e4[N],f4[N],g4[N],f4[N],e4[N],d4[N],#c4[N],(#A-2.#C-1.E-1.#a3)[N],a3[N],(#A-2.#C-1.E-1.g3)[N],f3[N],e3[N],d3[N],#c3[N],#a2[N],a2[N],g2[N],f2[N],e2[N],d2[N],#c2[N],#a1[N],a1[N],g1[N],f1[N],e1[N],d1[N],#c1[N],#a[N],a[N],g[N],f[N],e[N],d[N],#c[N],#A-1[N],A-1[N],G-1[N],(#G-2.B-2.F-1)[N],#G-1[N],A-1[N],B-1[N],#c[N],d[N],e[N],(#G-2.B-2.E-1.f)[N],#g[N],a[N],b[N],#c1[N],d1[N],e1[N],(#G-2.B-2.F-1.f1)[N],#g1[N],a1[N],b1[N],#c2[N],d2[N],e2[N],(#G-2.B-2.D-1.f2)[N],#g2[N],a2[N],b2[N],c3[N],d3[N],e3[N],(#G-2.B-2.E-1.f3)[N],#g3[N],a3[N],b3[N],#c4[N],d4[N],e4[N],(#G-2.B-2.C-1.f4)[N],e4[N],d4[N],#c4[N],b3[N],a3[N],#g3[N],(#G-2.B-2.D-1.f3)[N],e3[N],d3[N],#c3[N],b2[N],a2[N],#g2[N],f2[N],e2[N],d2[N],#c2[N],b1[N],a1[N],#g1[N],(#G-2.B-2.F-1.f1)[N],e1[N],d1[N],#c1[N],b[N],a[N],#g[N],(#G-2.B-2.F-1.f)[N],e[N],d[N],(#G-2.B-2.G-1.#c)[N],B-1[N],A-1[N],(#G-2.B-2.F-1)[N],#G-1[N],A-1[N],(#G-2.B-2.E-1.B-1)[N],#c[N],d[N],e[N],(#G-2.B-2.D-1.f)[N],#g[N],a[N],(#G-2.B-2.#C-1.b)[N],#c1[N],d1[N],e1[N],(#G-2.B-2.E-1.f1)[N],#g1[N],a1[N],b1[N],#c2[N],d2[N],e2[N],(#G-2.B-2.F-1.f2)[N],#g2[N],a2[N],b2[N],#c3[N],d3[N],e3[N],(#G-2.B-2.E-1.f3)[N],#g3[N],a3[N],b3[N],#c4[N],d4[N],e4[N],f4[N],e4[N],d4[N],#c4[N],b3[N],(#G-2.B-2.D-1.a3)[N],#g3[N],(#G-2.B-2.D-1.f3)[N],e3[N],d3[N],#c3[N],b2[N],a2[N],#g2[N],f2[N],e2[N],d2[N],#c2[N],b1[N],a1[N],#g1[N],f1[N],e1[N],d1[N],#c1[N],b[N],a[N],#g[N],f[N],e[N],d[N],#c[N],B-1[N],A-1[N]>,10<(#d.b.c1)[K]>,10<(d2.b1.c2)[K]>,10<(a2.e1.d2)[K]>,10<(a1.#f1.#g)[K]>,U,U,U,10<(e.E-2.g1)[K],G-2[N],A-2[N],D-2[N]>,U,U,U,10<(#D-2.#D-1.mute)[K],A-3[N],#A-3[N],B-3[N],C-2[N],#C-2[N]>,10<(A-3.#A-3.B-3)[K],a[N],G-2[N],#A-3[N],#G-2[N]>,10<(b4.a4.c5)[K]>,8<(c5~b4~#a4~a4~#g4~g4~#f4~f4~e4~#d4~d4~#c4~c4~b3~#a3~a3~#g3~g3~#f3~f3~e3~#d3~d3~#c3~c3~b2~#a2~a2~#g2~g2~#f2~f2~e2~#d2~d2~#c2~c2~b1~#a1~a1~#g1~g1~#f1~f1~e1~#d1~d1~#c1~c1~b~#a~a~#g~g~#f~f~e~#d~d~#c~c~B-1~#A-1~A-1~#G-1~G-1~#F-1~F-1~E-1~#D-1~D-1~#C-1~C-1~B-2~#A-2~A-2~#G-2~G-2~#F-2~F-2~E-2~#D-2~D-2~#C-2~C-2~B-3~#A-3~A-3)[KLM]>,U,U,U,U,(#C-2.#C-1)[K],(#c.#c1)[L],(#d.#d1)[L],(f.f1)[L],(#g.#g1)[L],(F-2.F-1.a.#c1.a1)[K],F-1[L],(a.c1.a2)[L],(#a.#a1)[L],f[L],(c1.c2)[K],(#A-3.#A-2.#c1.f1.#c2)[K];","QQQR,c[L],g[L],c1[L],e1[L],G-1[L],d[L],g[L],b[L];A-1[L],e[L],a[L],c1[L],E-1[L],B-1[L],e[L],g[L];F-1[L],c[L],f[L],a[L],C-1[L],G-1[L],c[L],e[L];F-1[L],c[L],f[L],a[L],G-1[L],d[L],g[L],b[L];c[L],g[L],c1[L],e1[L],G-1[L],d[L],g[L],b[L];A-1[L],e[L],a[L],c1[L],E-1[L],B-1[L],e[L],g[L];F-1[L],c[L],f[L],a[L],C-1[L],G-1[L],c[L],e[L];F-1[L],c[L],f[L],a[L],G-1[L],d[L],g[L],b[L];QQQQQQQQQQQQQQQQQQQQQQSTW;"],"id":1,"instruments":["piano","piano"],"alternatives":["",""]},{"bpm":120,"baseBeats":0.25,"scores":["V,g2[M],#a2[M],g2[M],e2[M],g2[M],#c2[M],e2[M],g2[M],e2[M],#c2[M],e2[M],a1[M],g1[M],f1[M],e1[M];V,f2[M],a2[M],f2[M],d2[M],f2[M],b1[M],d2[M],f2[M],d2[M],b1[M],d2[M],g1[M],f1[M],e1[M],d1[M];V,e2[M],g2[M],e2[M],c2[M],e2[M],a1[M],c2[M],#d2[M],c2[M],a1[M],c2[M],#f1[M],f1[M],e1[M],d1[M];V,d2[M],f2[M],d2[M],b1[M],d2[M],#g1[M],b1[M],d2[M],b1[M],#g1[M],b1[M],e1[M],d1[M],c1[M],b[M];V,e1[M],a1[M],c2[M],b1[M],e1[M],b1[M],d2[M],c2[L],a1[L],#g1[L],e1[L];a1[M],c2[M],e2[M],c2[M],a1[M],c2[M],#f1[M],a1[M],c2[M],a1[M],#f1[M],a1[M],#d1[M],c2[M],b1[M],a1[M];#g1[M],b1[M],d2[M],b1[M],#g1[M],b1[M],d1[M],f1[M],#g1[M],f1[M],d1[M],f1[M],b[M],f1[M],e1[M],d1[M];c1[M],e1[M],a1[M],e1[M],c1[M],e1[M],a[M],c1[M],#d1[M],c1[M],a[M],c1[M],#f[M],c1[M],b[M],a[M];#g[L],b1[L],#g1[L],e1[L],V,e1[M],a1[M],c2[M],b1[M],e1[M],b1[M],d2[M];c2[M],a1[M],c2[M],e2[M],d2[M],b1[M],d2[M],f2[M],e2[M],c2[M],e2[M],g2[M],f2[M],e2[M],d2[M],c2[M];b1[M],c2[M],d2[M],e2[M],f2[M],d2[M],#g2[M],d2[M],b2[M],d2[M],c2[M],a2[M],f2[M],d2[M],b1[M],d2[M];#g1[M],b1[M],c2[M],a1[M],e1[M],a1[M],b1[M],#g1[M],a1[M],e1[M],c1[M],e1[M],a[K],f3[M],e3[M],#d3[M],d3[M],f3[M],e3[M],#d3[M],d3[M],f3[M],e3[M],#d3[M],d3[M],f3[M],e3[M],#d3[M],d3[M];f3[M],e3[M],#d3[M],d3[M],#c3[M],c3[M],b2[M],#a2[M],a2[M],#g2[M],g2[M],#f2[M],f2[M],#a2[M],d3[M],#a2[M];c3[M],b2[M],#a2[M],a2[M],c3[M],b2[M],#a2[M],a2[M],c3[M],b2[M],#a2[M],a2[M],c3[M],b2[M],#a2[M],a2[M];c3[M],b2[M],#a2[M],a2[M],#g2[M],g2[M],#f2[M],f2[M],e2[M],#d2[M],d2[M],#c2[M],c2[M],f2[M],#d2[M],c2[M];#a1[M],b1[M],c2[M],#c2[M],d2[M],#d2[M],e2[M],f2[M],#f2[M],g2[M],#g2[M],a2[M],#a2[M],a2[M],#a2[M],b2[M];c3[M],#c3[M],d3[M],#d3[M],e3[M],f3[M],#f3[M],g3[M],#g3[M],a3[M],#a3[M],b3[M],c4[M],b3[M],c4[M],#c4[M];g1[M],e2[M],d2[M],c2[M],g1[M],e2[M],d2[M],c2[M],g1[M],e2[M],d2[M],c2[M],g1[M],e2[M],d2[M],c2[M];g1[M],f2[M],e2[M],d2[M],g1[M],f2[M],e2[M],d2[M],g1[M],f2[M],e2[M],d2[M],g1[M],f2[M],e2[M],d2[M];g1[M],d2[M],c2[M],b1[M],g1[M],d2[M],c2[M],b1[M],g1[M],d2[M],c2[M],b1[M],g1[M],d2[M],c2[M],b1[M];g1[M],e2[M],d2[M],c2[M],g1[M],e2[M],d2[M],c2[M],g1[M],e2[M],d2[M],c2[M],g1[M],e2[M],d2[M],c2[M];a1[M],a2[M],g2[M],#f2[M],a1[M],a2[M],g2[M],#f2[M],a1[M],a2[M],g2[M],#f2[M],a1[M],a2[M],g2[M],#f2[M];d2[M],d3[M],c3[M],b2[M],d2[M],d3[M],c3[M],b2[M],e2[M],c3[M],b2[M],a2[M],e2[M],c3[M],b2[M],a2[M];#a1[M],(#f2.#a2)[M],(b1.b2)[M],(c2.c3)[M],#c2[M],(#g2.#c3)[M],(#d2.#d3)[M],(#c2.#c3)[M],#f1[M],(#d2.#f2)[M],(#g1.#g2)[M],(a1.a2)[M],#a1[M],(f2.#a2)[M],(b1.b2)[M],(#a1.#a2)[M];#d1[M],(b1.#d2)[M],(e1.e2)[M],(f1.f2)[M],#f1[M],(#c2.#f2)[M],(f1.f2)[M],(#f1.#f2)[M],#g1[M],(#d2.#g2)[M],(#a1.#a2)[M],(#g1.#g2)[M],#g1[M],(f2.#g2)[M],(#c2.#a2)[M],(b1.b2)[M];(#f2.#a2)[M],#a1[M],(b1.b2)[M],(c2.c3)[M],#c2[M],(#g2.#c3)[M],(#d2.#d3)[M],(#c2.#c3)[M],#f2[M],#f1[M],(#g1.#g2)[M],(a1.a2)[M],#a1[M],(f2.#a2)[M],(b1.b2)[M],(#a1.#a2)[M];(b1.#d2)[M],#d1[M],(e1.e2)[M],(f1.f2)[M],#f1[M],(#c2.#f2)[M],(f1.f2)[M],(#f1.#f2)[M],#g1[M],(#f2.#g2)[M],(#a1.f2.#a2)[M],(#g1.#g2)[M],#f1[M],(#c2.#f2)[M],(f1.f2)[M],(#f1.#f2)[M];#g1[M],(f2.#g2)[M],(#a1.#a2)[M],(#g1.#g2)[M],#g1[M],(#f2.#g2)[M],(c2.c3)[M],(#c2.#c3)[M];","E-1[L],e[L],g[L],#a[L],#c[K],V,V,U;d1[L],d[L],f[L],#g[L],B-1[L],U,V,V,U;c1[L],c[L],e[L],#f[L],A-1[L],U,V,V,U;b[L],B-1[L],d[L],f[L],#G-1[L],U,V,V,U;c1[L],a[L],#g[L],e[L],a[M],e[M],a[M],c1[M],b[M],e[M],b[M],d1[M];c1[M],e1[M],a1[M],e1[M],c1[M],e1[M],a[M],c1[M],#f[M],a[M],c1[M],a[M],#f[M],a[M],#d[M],#f[M];e[L],#g[L],b[L],#g[L],e[L],B-1[L],#G-1[L],E-1[L];A-1[L],c[L],e[L],c[L],A-1[L],c[L],#D-1[L],U;V,b[M],#g[M],e[M],d[M],b[M],#g[M],d[M],c[L],e[L],#G-1[L],e[L];A-1[L],#f[L],B-1[L],#g[L],c[L],a[L],d[L],#a[L];#g[L],f[L],d[L],B-1[L],#G-1[L],A-1[L],D-1[L],E-1[L];F-1[L],#D-1[L],E-1[L],e[L],A-1[J];(#a1.d2)[L],U,T,(#a1.d2)[L],U,T;(#a1.d2)[L],U,T,S;(f1.a1.#d2)[L],U,T,(f1.a1.#d2)[L],U,T;(f1.a1.#d2)[L],U,T,S;(#a.d1.f1)[L],U,T,(#a.d1.f1)[L],U,T;(a.#d1.f1)[L],U,T,(a.#d1.f1)[L],U,T;(c1.e1)[L],U,T,T,U,(c1.e1)[L];(b.d1)[L],U,T,T,U,(b.d1)[L];(g.d1.f1)[L],U,T,T,U,(g.d1.f1)[L];(c1.e1)[L],U,T,T,U,(c1.e1)[L];(c1.d1.#f1)[L],U,T,T,(c1.d1.#f1)[L],U;(b.d1.g1)[L],U,T,(c1.e1.a1)[L],U,T;#f[L],(#a.#c1.#f1)[L],f[L],(#g.#c1.#g1)[L],#d[L],(#f.#a.#d1)[L],#c[L],(f.#a.f1)[L];B-1[L],(#f.b)[L],#A-1[L],(#c.#f.#c1)[L],c[L],(#f.#g.#d1)[L],#c[L],(b.#c1.f1)[L];#f[L],(#a.#f1)[L],f[L],(#g.#c1.#g1)[L],#d[L],(#f.#a.#d1)[L],#c[L],(f.#a.f1)[L];B-1[L],(#f.b)[L],#A-1[L],(#c.#f.#c1)[L],(c.#g.#d1)[L],(#c.#g.b.f1)[L],(#f.#a)[L],U;#c[L],(#g.#c1.f1)[L],c[L],(#g.#d1.#f1)[L];"],"id":2,"instruments":["piano","piano"],"alternatives":["",""]},{"bpm":120,"baseBeats":0.25,"scores":["5<(g.c1.e1)[N],g[N]>,5<e1[N],e1[N]>,5<g1[N],e2[N]>,5<e2[N],g2[N]>,5<e3[N],e3[N]>,5<g3[N],e4[N]>,5<g3[N],e4[N]>,5<e3[N],g2[N]>,5<e2[N],e2[N]>,5<g1[N],e1[N]>,5<e1[N],g[N]>,5<e[N],g[N]>,5<e1[N],g[N]>,5<e[N],g[N]>,5<f1[N],a[N]>,5<f[N],a[N]>;5<(b.d1.g1)[N],b[N]>,5<g1[N],g1[N]>,5<b1[N],g2[N]>,5<g2[N],b2[N]>,5<g3[N],g3[N]>,5<b3[N],g4[N]>,5<b3[N],g4[N]>,5<g3[N],b2[N]>,5<g2[N],g2[N]>,5<b1[N],g1[N]>,5<g1[N],b[N]>,5<g[N],b[N]>,5<g1[N],b[N]>,5<g[N],b[N]>,5<f1[N],a[N]>,5<f[N],a[N]>;5<(a.c1.e1)[N],a[N]>,5<e1[N],e1[N]>,5<a1[N],e2[N]>,5<e2[N],a2[N]>,5<e3[N],e3[N]>,5<a3[N],e4[N]>,5<a3[N],e4[N]>,5<e3[N],a2[N]>,5<e2[N],e2[N]>,5<a1[N],e1[N]>,5<e1[N],a[N]>,5<e[N],a[N]>,5<e1[N],a[N]>,5<e[N],a[N]>,5<d1[N],g[N]>,5<d[N],g[N]>;5<c[N],f[N]>,5<c1[N],c1[N]>,5<f1[N],c2[N]>,5<c2[N],f2[N]>,(c3~f2~c3~c2~f1~c1)[L],(c2~f1~c1~c1~f~c)[L],5<d[N],g[N]>,5<d1[N],d1[N]>,5<g1[N],d2[N]>,5<d2[N],g2[N]>,(d3~g2~d3~d2~g1~d1)[L],(d2~g1~d1~d1~g~d)[L];5<(g.c1.e1)[N],g[N]>,5<e1[N],e1[N]>,5<g1[N],e2[N]>,5<e2[N],g2[N]>,5<e3[N],e3[N]>,5<g3[N],e4[N]>,5<g3[N],e4[N]>,5<e3[N],g2[N]>,5<e2[N],e2[N]>,5<g1[N],e1[N]>,5<e1[N],g[N]>,5<e[N],g[N]>,5<e1[N],g[N]>,5<e[N],g[N]>,5<f1[N],a[N]>,5<f[N],a[N]>;5<(b.d1.g1)[N],b[N]>,5<g1[N],g1[N]>,5<b1[N],g2[N]>,5<g2[N],b2[N]>,5<g3[N],g3[N]>,5<b3[N],g4[N]>,5<b3[N],g4[N]>,5<g3[N],b2[N]>,5<g2[N],g2[N]>,5<b1[N],g1[N]>,5<g1[N],b[N]>,5<g[N],b[N]>,(g1.g2)[L],(b1.b2)[L];5<(c1.e1.a1.c2)[N],e1[N]>,5<c2[N],c2[N]>,5<e2[N],c3[N]>,5<c3[N],e3[N]>,c4[L],(a.b1)[M],(d1.c2)[M],F-1[M],c[M],f[M],g[M],f[M],c[M],F-1[M],F-1[M];U,U,U,U,S,(g1.g2)[L],U,e2[L],f2[L],g2[K],e2[L],f2[L];g2[I];g2[L],U,g2[K],a2[K],a2[K];g2[I];e2[L],U,d2[L],c2[L],e2[K],d2[L],c2[L];a1[L],U,a1[L],U,c2[L],U,(c2.f2)[L],U;(g1.f2)[L],U,e2[L],U,e2[L],U,d2[L],e2[L];g1[I];(f1.a1)[L],U,(f1.a1)[L],U,c2[K],c2[K];(e1.g1)[L],U,(e1.g1)[L],U,c2[J];(e1.#g1.d2)[L],U,U,U,e2[L],U,f2[L],U;(a1.c2.f2)[L],U,U,U,e2[L],U,U,U;(a1.c2.a2)[L],U,U,U,(a1.c2.a2)[L],U,(g1.g2)[L],U;(e1.g1.e2)[L],U,U,U,(g1.d2)[L],U,(e1.c2)[L],U;(d1.g1.d2)[L],U,(d1.g1.d2)[L],U,(g1.b1.g2)[K],(g1.b1.g2)[K];(c1.f1.g1.c2)[J],f3[L],8<(#g2~a2~#a2)[L]>,(b1.b2)[L];T,8<(#g3~a3~#a3)[L]>,(b2.b3)[L];T,V,8<(#g1~a1~#a1)[M]>,(d.f.#g.b.d1.b1)[M],8<(#g2~a2~#a2)[M]>;(d1.f1.#g1.b1.d2.b2)[M],8<(#g3~a3~#a3)[M]>,(d2.f2.#g2.b2.d3.b3)[M],8<(#g4~a4~#a4)[M]>,(d3.f3.#g3.b3.d4.b4)[M],8<(#g3~a3~#a3)[M]>,(d2.f2.#g2.b2.d3.b3)[M],8<(#g2~a2~#a2)[M]>;(d1.f1.#g1.b1.d2.b2)[M],8<(#g1~a1~#a1)[M]>,(d.f.#g.b.d1.b1)[L],8<(B-1~c~d~e~f~g~a~b~c1~d1~e1~f1~g1~a1~b1~c2~d2~e2~f2~g2)[L]>,8<(c5~b4~a4~g4~f4~e4~d4~c4~b3~a3~g3~f3~e3~d3~c3~b2~a2~g2~f2~e2)[K]>,8<(c5~b4~a4~g4~f4~e4~d4~c4~b3~a3~g3~f3~e3~d3~c3~b2~a2~g2~f2~e2)[K]>,8<(c5~b4~a4~g4~f4~e4~d4~c4~b3~a3~g3~f3~e3~d3~c3~b2~a2~g2~f2~e2)[K]>,8<(c5~b4~a4~g4~f4~e4~d4~c4~b3~a3~g3~f3~e3~d3~c3~b2~a2~g2~f2~e2)[K]>,8<(c5~b4~a4~g4~f4~e4~d4~c4~b3~a3~g3~f3~e3~d3~c3~b2~a2~g2~f2~e2)[K]>,8<(c5~b4~a4~g4~f4~e4~d4~c4~b3~a3~g3~f3~e3~d3~c3~b2~a2~g2~f2~e2)[K]>,8<(c5~b4~a4~g4~f4~e4~d4~c4~b3~a3~g3~f3~e3~d3~c3~b2~a2~g2~f2~e2)[K]>,3<#a2[M],#a2[M];#a2[M],f2[M],f2[M],#a2[M],#a2[M],f2[M],f2[M],#a2[M],a2[M],f2[M],f2[M],a2[M],a2[M],f2[M],f2[M],a2[M];#a2[M],f2[M],f2[M],#a2[M],#a2[M],f2[M],f2[M],#a2[M],c3[M],f2[M],f2[M],c3[M],c3[M],f2[M],f2[M],c3[M];#c3[M],f2[M],f2[M],#c3[M],#c3[M],f2[M],f2[M],#c3[M],c3[M],f2[M],f2[M],c3[M],c3[M],f2[M],f2[M],c3[M];#a2[M],f2[M],#c2[M],f2[M],#a1[M],c2[M],#c2[M],c2[M],#a1[M],f1[M],#c1[M],f1[M],#a[M],d1[M],f1[M],#a1[M];#g1[M],g1[M],#g1[M],c2[M],#d2[M],c2[M],#g1[M],#f1[M],f1[M],e1[M],f1[M],#a1[M],#c2[M],c2[M],#c2[M],#a1[M];#g1[M],g1[M],#g1[M],c2[M],#d2[M],#f2[M],f2[M],#d2[M],#c2[M],c2[M],#c2[M],#d2[M],f2[M],d2[M],#a1[M],#a2[M];#f2[M],f2[M],#d2[M],f2[M],#f2[M],#g2[M],#a2[M],#f2[M],f2[M],#d2[M],#c2[M],#d2[M],f2[M],#c2[M],#a1[M],f1[M];f1[M],g1[M],a1[M],#a1[M],c2[M],#c2[M],#d2[M],f2[M],#a1[M],f[M],#a[M],#c1[M],(a3.c4.f4)[N],(#a3.#d4.#f4)[N],(a3.c4.f4)[N],(#a3.#d4.#f4)[N],(a3.c4.f4)[N],(#a3.#d4.#f4)[N],(a3.c4.f4)[N],(#a3.#d4.#f4)[N],(a3.c4.f4)[N],(#a3.#d4.#f4)[N],(a3.c4.f4)[N],(#a3.#d4.#f4)[N],(a3.c4.f4)[N],(#a3.#d4.#f4)[N],(a3.c4.f4)[N],(#a3.#d4.#f4)[N],(a3.c4.f4)[N],(#a3.#d4.#f4)[N],(a3.c4.f4)[N],(#a3.#d4.#f4)[N],(a3.c4.f4)[N],(#a3.#d4.#f4)[N],(a3.c4.f4)[N],(#a3.#d4.#f4)[N],(a3.c4.f4)[N],(#a3.#d4.#f4)[N],(a3.c4.f4)[N],(#a3.#d4.#f4)[N],(a3.c4.f4)[N],(#a3.#d4.#f4)[N],(a3.c4.f4)[N],(#a3.#d4.#f4)[N],(a3.c4.f4)[N],(#a3.#d4.#f4)[N]>,10<(a.d1.b2)[K],C-2[N],#A-3[N],B-2[N],C-1[N],G-1[N],g4[N],b3[N],c2[N],b[N],B-1[N],c[N],a1[N],#a[N]>,(d1@#A-1)[IJKL];3<#d1[N],c1[N],#d1[N],g1[N],c2[N],#d2[N],d2[N],c2[N],b1[N],g1[N],b1[N],d2[N],g2[N],f2[N],#d2[N],d2[N]>;a1[M],#g1[M],a1[M],b1[M],(c2~d2~c2)[M],b1[M],c2[M],d2[M],3<#d2[N],c2[N],#d2[N],g2[N],c3[N],#d3[N],d3[N],c3[N],d3[N],c3[N],b2[N],a2[N],g2[N],f2[N],#d2[N],d2[N]>;(a.a1)[M],(b.b1)[M],(c1.c2)[M],(e1.e2)[M],(a1.a2)[JK];8<A-3[O],#A-3[O],B-3[O],C-2[O],C-2[O],D-2[O],#D-2[O],E-2[O],F-2[O],#F-2[O],G-2[O]>,8<#G-2[O],A-2[O],#A-2[O],B-2[O],C-1[O],#C-1[O],D-1[O],#D-1[O],E-1[O],F-1[O],#F-1[O]>,8<G-1[O],#G-1[O],A-1[O],#A-1[O],B-1[O],c[O],#c[O],d[O],#d[O],e[O],f[O]>,8<#f[O],g[O],#g[O],a[O],#a[O],b[O],c1[O],#c1[O],d1[O],#d1[O],e1[O]>,8<f1[O],#f1[O],g1[O],#g1[O],a1[O],#a1[O],b1[O],c2[O],#c2[O],d2[O],#d2[O]>,8<e2[O],f2[O],#f2[O],g2[O],#g2[O],a2[O],#a2[O],b2[O],c3[O],#c3[O],d3[O]>,8<#d3[O],e3[O],f3[O],#f3[O],g3[O],#g3[O],a3[O],#a3[O],b3[O],c4[O],#c4[O]>,8<d4[O],#d4[O],e4[O],f4[O],#f4[O],g4[O],#g4[O],a4[O],#a4[O],b4[O],c5[O]>;UV;UV,3<(d2.d3)[N]>,3<(f2.d3)[N]>,UV;UV,3<(d.#a)[N]>,3<(f.#a)[N]>,UV;;","c[N],G-1[N],c[N],c[N],g[N],c1[N],c1[N],g1[N],c1[N],c1[N],g1[N],c2[N],g1[N],c1[N],c1[N],g[N],c1[N],c1[N],g[N],c[N],c[N],G-1[N],c[N],G-1[N],c[N],G-1[N],c[N],G-1[N],d[N],G-1[N],c[N],G-1[N];B-1[N],G-1[N],B-1[N],B-1[N],g[N],b[N],b[N],g1[N],b[N],b[N],g1[N],b1[N],g1[N],b[N],b[N],g[N],b[N],b[N],g[N],B-1[N],B-1[N],G-1[N],c[N],G-1[N],B-1[N],G-1[N],B-1[N],G-1[N],B-1[N],G-1[N],d[N],G-1[N];A-1[N],E-1[N],A-1[N],A-1[N],e[N],a[N],a[N],e1[N],a[N],a[N],e1[N],a1[N],e1[N],a[N],a[N],e[N],a[N],a[N],e[N],A-1[N],A-1[N],E-1[N],A-1[N],E-1[N],A-1[N],E-1[N],A-1[N],E-1[N],G-1[N],E-1[N],B-1[N],E-1[N];f[N],c1[N],d1[N],d[N],c[N],f[N],f[N],c1[N],(f1~c1~f~f~c~F-1)[L],(f~c~F-1~F-1~c~F-1)[L],g[N],d[N],g[N],G-1[N],d[N],g[N],g[N],d1[N],(g1~d1~g~g~d~G-1)[L],(g~d~G-1~g1~d1~G-1)[L];c[N],G-1[N],c[N],c[N],g[N],c1[N],c1[N],g1[N],c1[N],c1[N],g1[N],c2[N],g1[N],c1[N],c1[N],g[N],c1[N],c1[N],g[N],c[N],c[N],G-1[N],c[N],G-1[N],c[N],G-1[N],c[N],G-1[N],d[N],G-1[N],c[N],G-1[N];(G-1.B-1)[LM],a1[M],g1[LM],g1[M],d1[M],g[M],g[M],d[M],G-1[M],G-1[M],D-1[M],G-2[M];(A-2.A-1)[M],E-1[M],A-1[M],A-1[M],e[M],a[M],e[M],A-1[M],(e1.g1.c2.e2~d1.g1.d2~c1.f1.g1.c2)[J];G-1[M],d[M],g[M],a[M],b[M],a[M],g[M],d[M],(G-2.G-1)[J];F-1[L],(f.c1.e1)[L],ST;R;E-1[L],(g.c1.e1)[L],ST;R;D-1[L],(d.f.a.c1)[L],ST;G-1[L],d[L],g[L],a[L],c1[L],f1[L],c1[L],a[L];C-1[L],G-1[L],c[L],d[L],e[L],g[L],c1[L],d1[L];e1[I];F-1[L],c[L],f[L],g[L],a[J];E-1[L],c[L],e[L],g[L],c1[J];#G-1[L],e[L],#g[L],b[L],e1[L],b[L],#g[L],e[L];A-1[L],e[L],a[L],b[L],c1[L],b[L],a[L],e[L];F-1[L],c[L],f[L],c[L],a[L],c[L],g[L],c[L];E-1[L],c[L],e[L],g[L],d1[L],e[L],g[L],c[L];G-1[L],d[L],g[L],a[L],b[J];C-1[J];"],"id":3,"instruments":["piano","piano"],"alternatives":["",""]}],"audition":{"start":[0,0],"end":[1,0]}}