{"baseBpm":171,"musics":[{"bpm":171,"baseBeats":0.375,"scores":["mute[HJKL],mute[KMNO],mute[LNO],mute[LM],mute[LNO],mute[LNO],mute[LM],mute[JNO],mute[LNO],mute[LM],mute[LNO],mute[LM],mute[LNO],mute[LM],mute[KMNO],mute[LM],mute[LNO],mute[LNO],mute[LM],mute[LNO],mute[JNO],mute[LM],mute[LNO],mute[LM],mute[LM],mute[LN],mute[LM],mute[KMNO],mute[LM],mute[LNO],mute[LM],mute[MN],mute[MN],mute[LNO],mute[LM],mute[KO],mute[MN],mute[LNO],mute[LNO],mute[LM],mute[MN],mute[MN],mute[LM],mute[LNO],mute[LNO],mute[LM],mute[LNO],mute[MN],mute[MN],mute[LNO],mute[LM],mute[LM],mute[LNO],mute[KO],mute[MN],mute[LNO],mute[LM],mute[LNO],mute[LM],mute[LM],mute[LNO],mute[KO],mute[MN],mute[LMO],mute[LNO],mute[LNO],mute[MN],mute[MN],mute[LNO],mute[LM],mute[KO];","(a.A-1)[HJKL],A-2[KMNO],#C-1[LNO],E-1[LM],#C-1[LNO],A-2[LNO],#C-1[LM],A-2[JNO],#C-1[LNO],E-1[LM],#C-1[LNO],A-2[LM],#C-1[LNO],A-2[LM],D-1[KMNO],#F-1[LM],A-1[LNO],#F-1[LNO],D-1[LM],#F-1[LNO],D-1[JNO],#F-1[LM],A-1[LNO],#F-1[LM],D-1[LM],#F-1[LN],D-1[LM],(A-2.e1)[KN],a1[MO],#C-1[LM],(e1.E-1)[LNO],(d2.#C-1)[LM],A-2[MN],#c2[MN],#C-1[LNO],(A-2.a1)[LM],e1[KO],a1[MN],#C-1[LNO],(e1.E-1)[LNO],(d2.#C-1)[LM],A-2[MN],#c2[MN],#C-1[LM],(a1.A-2)[LNO],D-1[LNO],e2[LM],(d2.#F-1)[LNO],A-1[MN],#c2[MN],#F-1[MN],b1[MO],(a1.D-1)[LM],(e1.#F-1)[LM],D-1[LNO],d1[KO],#f1[MN],#F-1[LNO],(d1.A-1)[LM],(#c2.#F-1)[LNO],D-1[LM],#F-1[LM],D-1[LNO],(A-2.e1)[KO],a1[MN],#C-1[LMO],(e1.E-1)[LNO],(d2.#C-1)[LNO],A-2[MNO],#c2[MO],#C-1[LNO],(A-2.a1)[LM],e1[KO];"],"id":1,"instruments":["piano","piano"],"alternatives":["",""]},{"bpm":171,"baseBeats":0.375,"scores":["mute[MN],mute[LM],mute[LNO],mute[LM],mute[LNO],mute[LNO],mute[LM],mute[LM],mute[LM],mute[LNO],mute[LNO],mute[LM],mute[LNO],mute[LM],mute[LNO],mute[KN],mute[MN],mute[LNO],mute[LM],mute[LNO],mute[LNO],mute[LM],mute[LNO],mute[JNO],mute[JKLO],mute[JM],mute[JKLO],mute[JNO],mute[JKLO],mute[KO],mute[KN],mute[JLMN],mute[LNO],mute[JNO],mute[JKLN],mute[KMN],mute[LM],mute[JLMN],mute[LM],mute[JN],mute[JKLN],mute[JNO],mute[HIJKO],mute[IKO],mute[LNO],mute[JNO],mute[LM],mute[JLMO],mute[KN],mute[KN],mute[LNO],mute[JN],mute[LM],mute[JLMN],mute[JLMN],mute[KO],mute[MN],mute[LM],mute[LNO],mute[LM],mute[LNO],mute[LNO],mute[LM],mute[KMNO],mute[LM],mute[LM],mute[LNO],mute[LNO],mute[LM];","a1[MN],#C-1[LM],(e1.E-1)[LNO],(d2.#C-1)[LM],A-2[MN],#c2[MO],#C-1[LNO],(a1.A-2)[LM],D-1[LM],e2[LM],(d2.#F-1)[LNO],(#c2.A-1)[LNO],(a1.#F-1)[LM],D-1[MN],e1[MO],#F-1[LM],D-1[LNO],d1[KN],#f1[MN],#F-1[LNO],(d1.A-1)[LM],(#c2.#F-1)[LNO],D-1[LNO],#F-1[LM],(e1.D-1)[LNO],(A-1.#C-1.#f1.A-2)[JNO],(a1.#c)[JKLO],(#g1.B-1.#D-1.B-2)[JM],(A-1.#C-1.#c.a1)[JKLO],(a1.A-2)[JNO],#c[JKLO],(B-1.#D-1.B-2.d2)[KO],#c2[KN],b1[JLMN],e1[LNO],(a1.A-1.#C-1.A-2)[JNO],#c[JKLN],(B-1.#D-1.B-2.b1)[KMN],#c2[LM],(A-1.#C-1.#c.a1)[JLMN],e1[LM],(a1.A-2)[JN],#c[JKLN],(B-1.#D-1.B-2.b1)[JNO],(e2.e1)[HIJKO],(A-1.D-1.A-2.a1)[IKO],e1[LNO],a1[JNO],e1[LM],#c2[JLMO],(d.e2)[KN],d2[KN],#c2[LNO],b1[JN],e1[LM],a1[JLMN],#f1[JLMN],(A-2.e1)[KO],a1[MN],#C-1[LM],(e1.E-1)[LNO],(d2.#C-1)[LM],A-2[MO],#c2[MN],#C-1[LNO],(A-2.a1)[LM],e1[KN],a1[MO],#C-1[LM],(e1.E-1)[LM],(d2.#C-1)[LNO],A-2[MO],#c2[MN],#C-1[LM];"],"id":2,"instruments":["piano","piano"],"alternatives":["",""]},{"bpm":171,"baseBeats":0.375,"scores":["mute[LNO],mute[LNO],mute[LM],mute[LM],mute[MN],mute[MN],mute[LNO],mute[LNO],mute[LM],mute[LNO],mute[KMNO],mute[LM],mute[LM],mute[LNO],mute[LM],mute[LNO],mute[LM],mute[KMN],mute[LM],mute[LM],mute[LNO],mute[MN],mute[MN],mute[LM],mute[LNO],mute[KO],mute[MN],mute[LM],mute[LNO],mute[LM],mute[LNO],mute[LM],mute[LNO],mute[LM],mute[LM],mute[LNO],mute[LNO],mute[MN],mute[MN],mute[MN],mute[MN],mute[LNO],mute[LNO],mute[KN],mute[MN],mute[LNO],mute[LM],mute[LNO],mute[LNO],mute[LM],mute[LNO],mute[IKLM],mute[KN],mute[KN],mute[JLMO],mute[LM],mute[IKLM],mute[KMNO],mute[LM],mute[JLMO],mute[LM],mute[IKLM],mute[KMNO],mute[LM],mute[KMNO],mute[JNO],mute[LM],mute[LNO],mute[LM],mute[KMNO],mute[LNO],mute[KMNO],mute[JNO],mute[JKLO],mute[JLMN],mute[JLMN],mute[KL],mute[HI];","(a1.A-2)[LNO],D-1[LNO],e2[LM],(d2.#F-1)[LM],A-1[MO],#c2[MNO],#F-1[MO],a1[MN],(b1.D-1)[LNO],(e1.#F-1)[LM],D-1[LNO],d1[KN],#f1[MO],#F-1[LM],(d1.A-1)[LM],(#c2.#F-1)[LNO],D-1[LM],#F-1[LNO],D-1[LM],(A-2.e1)[KO],a1[MO],#C-1[LM],(e1.E-1)[LM],(d2.#C-1)[LNO],A-2[MNO],#c2[MO],#C-1[LM],(A-2.a1)[LNO],e1[KO],a1[MN],#C-1[LM],(e1.E-1)[LNO],(d2.#C-1)[LM],A-2[MN],#c2[MO],#C-1[LM],(a1.A-2)[LNO],D-1[LM],e2[LM],#F-1[MO],d2[MN],A-1[LNO],(#F-1.#c2)[MN],a1[MN],D-1[MN],e1[MN],#F-1[LNO],D-1[LNO],d1[KN],#f1[MN],#F-1[LNO],(d1.A-1)[LM],(#c2.#F-1)[LNO],D-1[LNO],#F-1[LM],D-1[LNO],(a1.A-1.#C-1.A-2)[IKLM],(B-1.#D-1.B-2.b1)[KN],#c2[KN],(A-1.#C-1.a1)[JLMO],e1[LM],(a1.A-2)[IKLM],(B-1.#D-1.B-2.d2)[KMNO],#c2[LM],b1[JLMO],e1[LM],(a1.A-1.#C-1.A-2)[IKLM],(B-1.#D-1.B-2.b1)[KMNO],#c2[LM],(A-1.#C-1.a1)[KMNO],e1[JNO],(A-2.e2)[LM],d2[LNO],#c2[LM],b1[KMNO],a1[LNO],b1[KMNO],(B-1.#D-1.B-2.e1)[JNO],e2[JKLO],(#f.d)[JLMN],(e.B-1)[JLMN],(A-1.E-1)[KL],#c[HI];"],"id":3,"instruments":["piano","piano"],"alternatives":["",""]}],"audition":{"start":[0,0],"end":[2,82]}}